[{"recordNumber":"1-1000","title":"Puco","institution":"Museo Nacional de Historia Natural","category":"archaeology","thumbnail":"https://www.surdoc.cl/sites/default/files/record_images/000000161509-original.jpg","url":"https://www.surdoc.cl/registro/1-1000"},{"recordNumber":"1-1001","title":"Puco","institution":"Museo Nacional de Historia Natural","category":"archaeology","thumbnail":"https://www.surdoc.cl/sites/default/files/record_images/000000161514-original.jpg","url":"https://www.surdoc.cl/registro/1-1001"},{"recordNumber":"1-1002","title":"Olla (arqueológica y etnográfica)","institution":"Museo Nacional de Historia Natural","category":"archaeology","thumbnail":"https://www.surdoc.cl/sites/default/files/record_images/000000161519-original.jpg","url":"https://www.surdoc.cl/registro/1-1002"},{"recordNumber":"1-1003","title":"Plato (arqueológico y etnográfico)","institution":"Museo Nacional de Historia Natural","category":"archaeology","thumbnail":"https://www.surdoc.cl/sites/default/files/record_images/000000161524-original.jpg","url":"https://www.surdoc.cl/registro/1-1003"},{"recordNumber":"1-1004","title":"Plato (arqueológico y etnográfico)","institution":"Museo Nacional de Historia Natural","category":"archaeology","thumbnail":"https://www.surdoc.cl/sites/default/files/record_images/000000161529-original.jpg","url":"https://www.surdoc.cl/registro/1-1004"},{"recordNumber":"1-1005","title":"Plato (arqueológico y etnográfico)","institution":"Museo Nacional de Historia Natural","category":"archaeology","thumbnail":"https://www.surdoc.cl/sites/default/files/record_images/000000161534-original.jpg","url":"https://www.surdoc.cl/registro/1-1005"},{"recordNumber":"1-1006","title":"Plato (arqueológico y etnográfico)","institution":"Museo Nacional de Historia Natural","category":"archaeology","thumbnail":"https://www.surdoc.cl/sites/default/files/record_images/000000161539-original.jpg","url":"https://www.surdoc.cl/registro/1-1006"},{"recordNumber":"1-1007","title":"Plato (arqueológico y etnográfico)","institution":"Museo Nacional de Historia Natural","category":"archaeology","thumbnail":"https://www.surdoc.cl/sites/default/files/record_images/000000161544-original.jpg","url":"https://www.surdoc.cl/registro/1-1007"},{"recordNumber":"1-1008","title":"Plato (arqueológico y etnográfico)","institution":"Museo Nacional de Historia Natural","category":"archaeology","thumbnail":"https://www.surdoc.cl/sites/default/files/record_images/000000161549-original.jpg","url":"https://www.surdoc.cl/registro/1-1008"},{"recordNumber":"1-1009","title":"Plato (arqueológico y etnográfico)","institution":"Museo Nacional de Historia Natural","category":"archaeology","thumbnail":"https://www.surdoc.cl/sites/default/files/record_images/000000161554-original.jpg","url":"https://www.surdoc.cl/registro/1-1009"},{"recordNumber":"1-101","title":"Cubilete (complejo alucinógeno)","institution":"Museo Nacional de Historia Natural","category":"archaeology","thumbnail":"https://www.surdoc.cl/sites/default/files/record_images/000000123381-original.jpg","url":"https://www.surdoc.cl/registro/1-101"},{"recordNumber":"1-1010","title":"Plato (arqueológico y etnográfico)","institution":"Museo Nacional de Historia Natural","category":"archaeology","thumbnail":"https://www.surdoc.cl/sites/default/files/record_images/000000161559-original.jpg","url":"https://www.surdoc.cl/registro/1-1010"},{"recordNumber":"1-1011","title":"Puco","institution":"Museo Nacional de Historia Natural","category":"archaeology","thumbnail":"https://www.surdoc.cl/sites/default/files/record_images/000000161566-original.jpg","url":"https://www.surdoc.cl/registro/1-1011"},{"recordNumber":"1-1012","title":"Plato (arqueológico y etnográfico)","institution":"Museo Nacional de Historia Natural","category":"archaeology","thumbnail":"https://www.surdoc.cl/sites/default/files/record_images/000000161571-original.jpg","url":"https://www.surdoc.cl/registro/1-1012"},{"recordNumber":"1-1013","title":"Cesta","institution":"Museo Nacional de Historia Natural","category":"archaeology","thumbnail":"https://www.surdoc.cl/sites/default/files/record_images/000000161574-original.jpg","url":"https://www.surdoc.cl/registro/1-1013"},{"recordNumber":"1-1014","title":"Plato (arqueológico y etnográfico)","institution":"Museo Nacional de Historia Natural","category":"archaeology","thumbnail":"https://www.surdoc.cl/sites/default/files/record_images/000000161581-original.jpg","url":"https://www.surdoc.cl/registro/1-1014"},{"recordNumber":"1-1015","title":"Botella (arqueológica y etnográfica)","institution":"Museo Nacional de Historia Natural","category":"archaeology","thumbnail":"https://www.surdoc.cl/sites/default/files/record_images/000000161588-original.jpg","url":"https://www.surdoc.cl/registro/1-1015"},{"recordNumber":"1-1016","title":"Botella (arqueológica y etnográfica)","institution":"Museo Nacional de Historia Natural","category":"archaeology","thumbnail":"https://www.surdoc.cl/sites/default/files/record_images/000000161593-original.jpg","url":"https://www.surdoc.cl/registro/1-1016"},{"recordNumber":"1-1017","title":"Jarro (arqueológico y etnográfico)","institution":"Museo Nacional de Historia Natural","category":"archaeology","thumbnail":"https://www.surdoc.cl/sites/default/files/record_images/000000161598-original.jpg","url":"https://www.surdoc.cl/registro/1-1017"},{"recordNumber":"1-1018","title":"Botella (arqueológica y etnográfica)","institution":"Museo Nacional de Historia Natural","category":"archaeology","thumbnail":"https://www.surdoc.cl/sites/default/files/record_images/000000161603-original.jpg","url":"https://www.surdoc.cl/registro/1-1018"},{"recordNumber":"1-1019","title":"Vaso","institution":"Museo Nacional de Historia Natural","category":"archaeology","thumbnail":"https://www.surdoc.cl/sites/default/files/record_images/000000161608-original.jpg","url":"https://www.surdoc.cl/registro/1-1019"},{"recordNumber":"1-102","title":"Cubilete (complejo alucinógeno)","institution":"Museo Nacional de Historia Natural","category":"archaeology","thumbnail":"https://www.surdoc.cl/sites/default/files/record_images/000000123413-original.jpg","url":"https://www.surdoc.cl/registro/1-102"},{"recordNumber":"1-1020","title":"Cesta","institution":"Museo Nacional de Historia Natural","category":"archaeology","thumbnail":"https://www.surdoc.cl/sites/default/files/record_images/000000161613-original.jpg","url":"https://www.surdoc.cl/registro/1-1020"},{"recordNumber":"1-1021","title":"Vaso","institution":"Museo Nacional de Historia Natural","category":"archaeology","thumbnail":"https://www.surdoc.cl/sites/default/files/record_images/000000161619-original.jpg","url":"https://www.surdoc.cl/registro/1-1021"},{"recordNumber":"1-1022","title":"Kero","institution":"Museo Nacional de Historia Natural","category":"archaeology","thumbnail":"https://www.surdoc.cl/sites/default/files/record_images/000000161624-original.jpg","url":"https://www.surdoc.cl/registro/1-1022"},{"recordNumber":"1-1023","title":"Olla (arqueológica y etnográfica)","institution":"Museo Nacional de Historia Natural","category":"archaeology","thumbnail":"https://www.surdoc.cl/sites/default/files/record_images/000000161629-original.jpg","url":"https://www.surdoc.cl/registro/1-1023"},{"recordNumber":"1-1024","title":"Plato (arqueológico y etnográfico)","institution":"Museo Nacional de Historia Natural","category":"archaeology","thumbnail":"https://www.surdoc.cl/sites/default/files/record_images/000000161634-original.jpg","url":"https://www.surdoc.cl/registro/1-1024"},{"recordNumber":"1-1025","title":"Plato (arqueológico y etnográfico)","institution":"Museo Nacional de Historia Natural","category":"archaeology","thumbnail":"https://www.surdoc.cl/sites/default/files/record_images/000000161639-original.jpg","url":"https://www.surdoc.cl/registro/1-1025"},{"recordNumber":"1-1026","title":"Plato (arqueológico y etnográfico)","institution":"Museo Nacional de Historia Natural","category":"archaeology","thumbnail":"https://www.surdoc.cl/sites/default/files/record_images/000000161644-original.jpg","url":"https://www.surdoc.cl/registro/1-1026"},{"recordNumber":"1-1027","title":"Plato (arqueológico y etnográfico)","institution":"Museo Nacional de Historia Natural","category":"archaeology","thumbnail":"https://www.surdoc.cl/sites/default/files/record_images/000000161649-original.jpg","url":"https://www.surdoc.cl/registro/1-1027"},{"recordNumber":"1-1028","title":"Cuenco","institution":"Museo Nacional de Historia Natural","category":"archaeology","thumbnail":"https://www.surdoc.cl/sites/default/files/record_images/000000161654-original.jpg","url":"https://www.surdoc.cl/registro/1-1028"},{"recordNumber":"1-103","title":"Cubilete (complejo alucinógeno)","institution":"Museo Nacional de Historia Natural","category":"archaeology","thumbnail":"https://www.surdoc.cl/sites/default/files/record_images/000000123417-original.jpg","url":"https://www.surdoc.cl/registro/1-103"},{"recordNumber":"1-1030","title":"Plato (arqueológico y etnográfico)","institution":"Museo Nacional de Historia Natural","category":"archaeology","thumbnail":"https://www.surdoc.cl/sites/default/files/record_images/000000161664-original.jpg","url":"https://www.surdoc.cl/registro/1-1030"},{"recordNumber":"1-1031","title":"Plato (arqueológico y etnográfico)","institution":"Museo Nacional de Historia Natural","category":"archaeology","thumbnail":"https://www.surdoc.cl/sites/default/files/record_images/000000161666-original.jpg","url":"https://www.surdoc.cl/registro/1-1031"},{"recordNumber":"1-1032","title":"Olla (arqueológica y etnográfica)","institution":"Museo Nacional de Historia Natural","category":"archaeology","thumbnail":"https://www.surdoc.cl/sites/default/files/record_images/000000161670-original.jpg","url":"https://www.surdoc.cl/registro/1-1032"},{"recordNumber":"1-1033","title":"Olla (arqueológica y etnográfica)","institution":"Museo Nacional de Historia Natural","category":"archaeology","thumbnail":"https://www.surdoc.cl/sites/default/files/record_images/000000161675-original.jpg","url":"https://www.surdoc.cl/registro/1-1033"},{"recordNumber":"1-1034","title":"Plato (arqueológico y etnográfico)","institution":"Museo Nacional de Historia Natural","category":"archaeology","thumbnail":"https://www.surdoc.cl/sites/default/files/record_images/000000161680-original.jpg","url":"https://www.surdoc.cl/registro/1-1034"},{"recordNumber":"1-1035","title":"Plato (arqueológico y etnográfico)","institution":"Museo Nacional de Historia Natural","category":"archaeology","thumbnail":"https://www.surdoc.cl/sites/default/files/record_images/000000161685-original.jpg","url":"https://www.surdoc.cl/registro/1-1035"},{"recordNumber":"1-1036","title":"Plato (arqueológico y etnográfico)","institution":"Museo Nacional de Historia Natural","category":"archaeology","thumbnail":"https://www.surdoc.cl/sites/default/files/record_images/000000161690-original.jpg","url":"https://www.surdoc.cl/registro/1-1036"},{"recordNumber":"1-1037","title":"Puco","institution":"Museo Nacional de Historia Natural","category":"archaeology","thumbnail":"https://www.surdoc.cl/sites/default/files/record_images/000000161695-original.jpg","url":"https://www.surdoc.cl/registro/1-1037"},{"recordNumber":"1-1038","title":"Olla (arqueológica y etnográfica)","institution":"Museo Nacional de Historia Natural","category":"archaeology","thumbnail":"https://www.surdoc.cl/sites/default/files/record_images/000000161700-original.jpg","url":"https://www.surdoc.cl/registro/1-1038"},{"recordNumber":"1-1039","title":"Botella (arqueológica y etnográfica)","institution":"Museo Nacional de Historia Natural","category":"archaeology","thumbnail":"https://www.surdoc.cl/sites/default/files/record_images/000000161706-original.jpg","url":"https://www.surdoc.cl/registro/1-1039"}]